[
  {"question": "ما هي عاصمة الأردن؟", "answer": "عمان"},
  {"question": "أطول نهر في العالم؟", "answer": "النيل"},
  {"question": "ما هي أصغر قارة؟", "answer": "استراليا"},
  {"question": "من اخترع الهاتف؟", "answer": "غراهام بيل"},
  {"question": "ما هو أكبر كوكب في المجموعة الشمسية؟", "answer": "المشتري"},
  {"question": "ما هو أسرع حيوان بري؟", "answer": "الفهد"},
  {"question": "ما هو العنصر الكيميائي برمز O؟", "answer": "الأكسجين"},
  {"question": "ما هي لغة البرازيل الرسمية؟", "answer": "البرتغالية"},
  {"question": "كم عدد القارات؟", "answer": "7"},
  {"question": "ما هو البحر الذي يفصل بين أوروبا وأفريقيا؟", "answer": "البحر الأبيض المتوسط"},
  {"question": "ما هو الحيوان الذي يسمى سفينة الصحراء؟", "answer": "الجمل"},
  {"question": "ما هي أطول سلسلة جبال في العالم؟", "answer": "جبال الأنديز"},
  {"question": "ما هو رمز الذهب الكيميائي؟", "answer": "Au"},
  {"question": "ما هو أكبر محيط في العالم؟", "answer": "المحيط الهادئ"},
  {"question": "ما هو أسرع طائر؟", "answer": "الصقر الشاهين"},
  {"question": "ما هو الحيوان الوطني للأستراليا؟", "answer": "الكنغر"},
  {"question": "من كتب مسرحية روميو وجولييت؟", "answer": "ويليام شكسبير"},
  {"question": "ما هي الدولة التي تسمى بلاد الشمس المشرقة؟", "answer": "اليابان"},
  {"question": "ما هو أطول نهر في آسيا؟", "answer": "اليانغتسي"},
  {"question": "ما هو الكوكب الأحمر؟", "answer": "المريخ"},
  {"question": "ما هو أكبر حيوان على وجه الأرض؟", "answer": "الحوت الأزرق"},
  {"question": "من هو مكتشف الكهرباء؟", "answer": "بنيامين فرانكلين"},
  {"question": "ما هي عاصمة فرنسا؟", "answer": "باريس"},
  {"question": "ما هو أسرع حيوان بحري؟", "answer": "سمكة الشراع"},
  {"question": "ما هو العدد الأولي بين 20 و30؟", "answer": "23"},
  {"question": "ما هو الحيوان الذي لا يستطيع القفز؟", "answer": "الفيل"},
  {"question": "ما هو أطول نهر في أمريكا الجنوبية؟", "answer": "الأمازون"},
  {"question": "ما هو أول عنصر في الجدول الدوري؟", "answer": "الهيدروجين"},
  {"question": "ما هي أكبر صحراء في العالم؟", "answer": "الصحراء الكبرى"},
  {"question": "ما هي الدولة التي تحتوي على أكبر عدد من الجزر؟", "answer": "السويد"},
  {"question": "ما هو أسرع حيوان في الماء؟", "answer": "سمك الشراع"},
  {"question": "من اخترع المصباح الكهربائي؟", "answer": "توماس إديسون"},
  {"question": "ما هو أطول جسر في العالم؟", "answer": "جسر دانيانغ-كونشان الكبير"},
  {"question": "ما هو أكبر بحيرة في العالم؟", "answer": "بحيرة قزوين"},
  {"question": "ما هي أصغر دولة في العالم؟", "answer": "الفاتيكان"},
  {"question": "ما هو الحيوان الذي ينام واقفاً؟", "answer": "الحصان"},
  {"question": "ما هو الكوكب المعروف بالكوكب الأزرق؟", "answer": "الأرض"},
  {"question": "ما هي الدولة التي يُطلق عليها أرض الفراعنة؟", "answer": "مصر"},
  {"question": "ما هو أطول برج في العالم؟", "answer": "برج خليفة"},
  {"question": "ما هي عاصمة ألمانيا؟", "answer": "برلين"},
  {"question": "ما هو الحيوان الذي له رقبة طويلة جداً؟", "answer": "الزرافة"},
  {"question": "ما هو الكوكب الأصغر في النظام الشمسي؟", "answer": "عطارد"},
  {"question": "ما هو البحر الذي يحتوي على أدنى نقطة على الأرض؟", "answer": "البحر الميت"},
  {"question": "من هو مكتشف أمريكا؟", "answer": "كريستوفر كولومبوس"},
  {"question": "ما هي الدولة التي تسمى بلاد الشمس المشرقة؟", "answer": "اليابان"},
  {"question": "ما هو الحيوان الذي يعتبر ملك الغابة؟", "answer": "الأسد"},
  {"question": "ما هي اللغة الرسمية في كندا؟", "answer": "الإنجليزية والفرنسية"},
  {"question": "ما هو أسرع حيوان يعيش على الأرض؟", "answer": "الفهد"},
  {"question": "ما هي أصغر عظمة في جسم الإنسان؟", "answer": "عظمة الركاب"},
  {"question": "ما هو البحر الذي يفصل بين السعودية وإيران؟", "answer": "الخليج العربي"},
  {"question": "ما هو الحيوان الذي يستطيع الطيران ولكنه ثديي؟", "answer": "الخفاش"},
  {"question": "ما هو أعلى جبل في العالم؟", "answer": "إيفرست"},
  {"question": "ما هي الدولة التي تقع بين فرنسا وإسبانيا؟", "answer": "أندورا"},
  {"question": "ما هو الحيوان الذي يمكن أن يعيش دون ماء لفترة طويلة؟", "answer": "الجمل"},
  {"question": "ما هو الكوكب المعروف بالحلقة الشهيرة؟", "answer": "زحل"},
  {"question": "ما هي العملة الرسمية في اليابان؟", "answer": "الين"},
  {"question": "ما هو أول حيوان استأنسه الإنسان؟", "answer": "الكلب"},
  {"question": "ما هي الدولة التي بها أكبر كثافة سكانية؟", "answer": "الصين"},
  {"question": "ما هو الحيوان الذي يُعرف بصديق الإنسان؟", "answer": "الكلب"},
  {"question": "ما هو أطول جسر بحري في العالم؟", "answer": "جسر هونغ كونغ-تشوهاي-ماكاو"},
  {"question": "ما هو الكوكب المعروف بالكوكب الأحمر؟", "answer": "المريخ"},
  {"question": "ما هي الدولة التي بها أكبر صحراء؟", "answer": "السعودية"},
  {"question": "ما هو الحيوان الذي يعتبر أكبر مفترس بحري؟", "answer": "القرش الأبيض الكبير"},
  {"question": "ما هي الدولة التي تُعرف بأرض الأنهار؟", "answer": "بنغلاديش"},
  {"question": "ما هو أطول نهر في أوروبا؟", "answer": "الفولغا"},
  {"question": "ما هو الحيوان الذي يستطيع تغيير لونه؟", "answer": "الحرباء"},
  {"question": "ما هي الدولة التي تقع في قارة أستراليا؟", "answer": "أستراليا"},
  {"question": "ما هو أسرع حيوان مائي؟", "answer": "سمك الشراع"},
  {"question": "ما هو الحيوان الذي له ذيل أطول من جسمه؟", "answer": "التمساح"},
  {"question": "ما هي الدولة التي يُعرف علمها بالنجمة والهلال؟", "answer": "تركيا"},
  {"question": "ما هو الحيوان الذي يُسمى بسفينة الصحراء؟", "answer": "الجمل"},
  {"question": "ما هو الكوكب المعروف بالكوكب الغازي العملاق؟", "answer": "المشتري"},
  {"question": "ما هي الدولة التي يطلق عليها بلاد الفايكنج؟", "answer": "النرويج"},
  {"question": "ما هو الحيوان الذي له جلد سميك وأذن صغيرة؟", "answer": "الفيل"},
  {"question": "ما هي الدولة التي يمر بها نهر الأمازون؟", "answer": "البرازيل"},
  {"question": "ما هو أسرع طائر في السماء؟", "answer": "الصقر"},
  {"question": "ما هي الدولة التي بها أطول ساحل بحري؟", "answer": "كندا"},
  {"question": "ما هو الحيوان الذي يُعرف بأنه ملك الغابة؟", "answer": "الأسد"},
  {"question": "ما هي الدولة التي تحتوي على أكبر عدد من الجزر؟", "answer": "السويد"},
  {"question": "ما هو أطول نهر في إفريقيا؟", "answer": "النيل"},
  {"question": "ما هو الحيوان الذي يبيض ولكنه ثديي؟", "answer": "البرسوس"},
  {"question": "ما هي الدولة التي يمر بها جبل إيفرست؟", "answer": "نيبال"},
  {"question": "ما هو الحيوان الذي لا يستطيع المشي للخلف؟", "answer": "الكنغر"},
  {"question": "ما هو البحر الذي يفصل بين المملكة العربية السعودية وقطر؟", "answer": "الخليج العربي"},
  {"question": "ما هي الدولة التي تُعرف بأرض الفراعنة؟", "answer": "مصر"},
  {"question": "ما هو أطول جسر معلق في العالم؟", "answer": "جسر أكاشي كايكو"},
  {"question": "ما هو الحيوان الذي يُعرف بسرعته الكبيرة؟", "answer": "الفهد"},
  {"question": "ما هي الدولة التي يُعرف علمها بالأحمر والأبيض والأسود؟", "answer": "ألمانيا"},
  {"question": "ما هو الكوكب الذي يُعرف بالكوكب الأزرق؟", "answer": "الأرض"},
  {"question": "ما هو الحيوان الذي له قرون طويلة ومنحنية؟", "answer": "الماعز الجبلي"},
  {"question": "ما هي الدولة التي تسمى بلاد الألف بحيرة؟", "answer": "فنلندا"},
  {"question": "ما هو الحيوان الذي يُعرف بذكائه الكبير؟", "answer": "الدلفين"},
  {"question": "ما هي الدولة التي تحتوي على أطول نهر في العالم؟", "answer": "مصر"}
]
